modeltracker/__init__.py
modeltracker/about.py
modeltracker/main.py
modeltracker/modeltracker.py
modeltracker/settings.py
modeltracker/settings_local.py
modeltracker/utils.py
modeltracker/accesslayer/__init__.py
modeltracker/accesslayer/dao.py
modeltracker/dblayer/__init__.py
modeltracker/dblayer/connection.py
modeltracker/dblayer/enumtypes.py
modeltracker/dblayer/model.py
modeltracker/dblayer/populate.py
model_tracker-0.0.1.dist-info/LICENSE
model_tracker-0.0.1.dist-info/METADATA
model_tracker-0.0.1.dist-info/WHEEL
model_tracker-0.0.1.dist-info/top_level.txt
model_tracker-0.0.1.dist-info/RECORD
