Metadata-Version: 2.1
Name: model-tracker
Version: 0.0.1
Summary: Simple approximate queue model metrics 
Home-page: UNKNOWN
Author: jackdotwa
Author-email: jacques@spatialedge.co.za
License: UNKNOWN
Platform: UNKNOWN
Classifier: Programming Language :: Python :: 3
Classifier: Operating System :: OS Independent
Requires-Python: >=3.6
Requires-Dist: psycopg2-binary (==2.8.5)
Requires-Dist: SQLAlchemy (==1.3.18)
Requires-Dist: pandas
